<?xml version="1.0" encoding="utf-8"?>
<odoo>
    <record id="payment_provider_payu" model="payment.provider">
        <field name="name">PayU</field>
        <field name="module_id" ref="base.module_payment_payu"/>
        <field name="payment_method_ids"
               eval="[Command.set([
                    ref('payment_payu.payment_method_payu'),
               ])]"/>
        <field name="code">payu</field>
        <field name="redirect_form_view_id" ref="redirect_form"/>
    </record>
</odoo>
